adafruit_ags02ma.py
adafruit_circuitpython_ags02ma-1.0.13.dist-info/licenses/LICENSE
adafruit_circuitpython_ags02ma-1.0.13.dist-info/METADATA
adafruit_circuitpython_ags02ma-1.0.13.dist-info/WHEEL
adafruit_circuitpython_ags02ma-1.0.13.dist-info/top_level.txt
adafruit_circuitpython_ags02ma-1.0.13.dist-info/RECORD
